[
  {
    "anonymous": false,
    "inputs": [
      {
        "indexed": true,
        "internalType": "address",
        "name": "user",
        "type": "address"
      },
      {
        "indexed": true,
        "internalType": "uint256",
        "name": "pid",
        "type": "uint256"
      },
      {
        "indexed": false,
        "internalType": "uint256",
        "name": "amount",
        "type": "uint256"
      }
    ],
    "name": "Deposit",
    "type": "event"
  },
  {
    "anonymous": false,
    "inputs": [
      {
        "indexed": true,
        "internalType": "address",
        "name": "user",
        "type": "address"
      },
      {
        "indexed": true,
        "internalType": "uint256",
        "name": "pid",
        "type": "uint256"
      },
      {
        "indexed": false,
        "internalType": "uint256",
        "name": "amount",
        "type": "uint256"
      }
    ],
    "name": "EmergencyWithdraw",
    "type": "event"
  },
  {
    "anonymous": false,
    "inputs": [
      {
        "indexed": true,
        "internalType": "address",
        "name": "target",
        "type": "address"
      },
      {
        "indexed": false,
        "internalType": "uint256",
        "name": "value",
        "type": "uint256"
      },
      {
        "indexed": false,
        "internalType": "string",
        "name": "signature",
        "type": "string"
      },
      {
        "indexed": false,
        "internalType": "bytes",
        "name": "data",
        "type": "bytes"
      }
    ],
    "name": "ExecuteTransaction",
    "type": "event"
  },
  {
    "anonymous": false,
    "inputs": [
      {
        "indexed": true,
        "internalType": "address",
        "name": "executor",
        "type": "address"
      },
      {
        "indexed": false,
        "internalType": "uint256",
        "name": "at",
        "type": "uint256"
      }
    ],
    "name": "Initialized",
    "type": "event"
  },
  {
    "anonymous": false,
    "inputs": [
      {
        "indexed": true,
        "internalType": "uint256",
        "name": "rewardPid",
        "type": "uint256"
      },
      {
        "indexed": true,
        "internalType": "address",
        "name": "token",
        "type": "address"
      },
      {
        "indexed": true,
        "internalType": "address",
        "name": "user",
        "type": "address"
      },
      {
        "indexed": false,
        "internalType": "uint256",
        "name": "amount",
        "type": "uint256"
      }
    ],
    "name": "RewardPaid",
    "type": "event"
  },
  {
    "anonymous": false,
    "inputs": [
      {
        "indexed": true,
        "internalType": "address",
        "name": "user",
        "type": "address"
      },
      {
        "indexed": true,
        "internalType": "uint256",
        "name": "pid",
        "type": "uint256"
      },
      {
        "indexed": false,
        "internalType": "uint256",
        "name": "amount",
        "type": "uint256"
      }
    ],
    "name": "Withdraw",
    "type": "event"
  },
  {
    "inputs": [
      {
        "internalType": "uint256",
        "name": "_allocPoint",
        "type": "uint256"
      },
      {
        "internalType": "contract IERC20",
        "name": "_want",
        "type": "address"
      },
      {
        "internalType": "bool",
        "name": "_withUpdate",
        "type": "bool"
      },
      {
        "internalType": "address",
        "name": "_strategy",
        "type": "address"
      }
    ],
    "name": "add",
    "outputs": [],
    "stateMutability": "nonpayable",
    "type": "function"
  },
  {
    "inputs": [
      {
        "internalType": "address",
        "name": "_rewardToken",
        "type": "address"
      },
      {
        "internalType": "uint256",
        "name": "_rewardPerBlock",
        "type": "uint256"
      }
    ],
    "name": "addRewardPool",
    "outputs": [],
    "stateMutability": "nonpayable",
    "type": "function"
  },
  {
    "inputs": [
      {
        "internalType": "uint256",
        "name": "_pid",
        "type": "uint256"
      },
      {
        "internalType": "uint256",
        "name": "_wantAmt",
        "type": "uint256"
      }
    ],
    "name": "deposit",
    "outputs": [],
    "stateMutability": "nonpayable",
    "type": "function"
  },
  {
    "inputs": [
      {
        "internalType": "uint256",
        "name": "_pid",
        "type": "uint256"
      }
    ],
    "name": "emergencyWithdraw",
    "outputs": [],
    "stateMutability": "nonpayable",
    "type": "function"
  },
  {
    "inputs": [
      {
        "internalType": "address",
        "name": "target",
        "type": "address"
      },
      {
        "internalType": "uint256",
        "name": "value",
        "type": "uint256"
      },
      {
        "internalType": "string",
        "name": "signature",
        "type": "string"
      },
      {
        "internalType": "bytes",
        "name": "data",
        "type": "bytes"
      }
    ],
    "name": "executeTransaction",
    "outputs": [
      {
        "internalType": "bytes",
        "name": "",
        "type": "bytes"
      }
    ],
    "stateMutability": "nonpayable",
    "type": "function"
  },
  {
    "inputs": [
      {
        "internalType": "uint256",
        "name": "_from",
        "type": "uint256"
      },
      {
        "internalType": "uint256",
        "name": "_to",
        "type": "uint256"
      }
    ],
    "name": "getMultiplier",
    "outputs": [
      {
        "internalType": "uint256",
        "name": "",
        "type": "uint256"
      }
    ],
    "stateMutability": "pure",
    "type": "function"
  },
  {
    "inputs": [
      {
        "internalType": "address",
        "name": "_token",
        "type": "address"
      },
      {
        "internalType": "uint256",
        "name": "_amount",
        "type": "uint256"
      },
      {
        "internalType": "address",
        "name": "_to",
        "type": "address"
      }
    ],
    "name": "inCaseTokensGetStuck",
    "outputs": [],
    "stateMutability": "nonpayable",
    "type": "function"
  },
  {
    "inputs": [
      {
        "internalType": "uint256",
        "name": "_startBlock",
        "type": "uint256"
      },
      {
        "internalType": "address",
        "name": "_bfi",
        "type": "address"
      },
      {
        "internalType": "uint256",
        "name": "_bfiRewardRate",
        "type": "uint256"
      },
      {
        "internalType": "address",
        "name": "_bdo",
        "type": "address"
      },
      {
        "internalType": "uint256",
        "name": "_bdoRewardRate",
        "type": "uint256"
      }
    ],
    "name": "initialize",
    "outputs": [],
    "stateMutability": "nonpayable",
    "type": "function"
  },
  {
    "inputs": [],
    "name": "initialized",
    "outputs": [
      {
        "internalType": "bool",
        "name": "",
        "type": "bool"
      }
    ],
    "stateMutability": "view",
    "type": "function"
  },
  {
    "inputs": [],
    "name": "massUpdatePools",
    "outputs": [],
    "stateMutability": "nonpayable",
    "type": "function"
  },
  {
    "inputs": [],
    "name": "operator",
    "outputs": [
      {
        "internalType": "address",
        "name": "",
        "type": "address"
      }
    ],
    "stateMutability": "view",
    "type": "function"
  },
  {
    "inputs": [
      {
        "internalType": "uint256",
        "name": "_pid",
        "type": "uint256"
      },
      {
        "internalType": "uint256",
        "name": "_rewardPid",
        "type": "uint256"
      },
      {
        "internalType": "address",
        "name": "_user",
        "type": "address"
      }
    ],
    "name": "pendingReward",
    "outputs": [
      {
        "internalType": "uint256",
        "name": "",
        "type": "uint256"
      }
    ],
    "stateMutability": "view",
    "type": "function"
  },
  {
    "inputs": [
      {
        "internalType": "uint256",
        "name": "",
        "type": "uint256"
      }
    ],
    "name": "poolInfo",
    "outputs": [
      {
        "internalType": "contract IERC20",
        "name": "want",
        "type": "address"
      },
      {
        "internalType": "uint256",
        "name": "allocPoint",
        "type": "uint256"
      },
      {
        "internalType": "uint256",
        "name": "lastRewardBlock",
        "type": "uint256"
      },
      {
        "internalType": "address",
        "name": "strategy",
        "type": "address"
      }
    ],
    "stateMutability": "view",
    "type": "function"
  },
  {
    "inputs": [],
    "name": "poolLength",
    "outputs": [
      {
        "internalType": "uint256",
        "name": "",
        "type": "uint256"
      }
    ],
    "stateMutability": "view",
    "type": "function"
  },
  {
    "inputs": [
      {
        "internalType": "uint256",
        "name": "",
        "type": "uint256"
      }
    ],
    "name": "rewardPoolInfo",
    "outputs": [
      {
        "internalType": "address",
        "name": "rewardToken",
        "type": "address"
      },
      {
        "internalType": "uint256",
        "name": "rewardPerBlock",
        "type": "uint256"
      },
      {
        "internalType": "uint256",
        "name": "totalPaidRewards",
        "type": "uint256"
      }
    ],
    "stateMutability": "view",
    "type": "function"
  },
  {
    "inputs": [],
    "name": "rewardPoolLength",
    "outputs": [
      {
        "internalType": "uint256",
        "name": "",
        "type": "uint256"
      }
    ],
    "stateMutability": "view",
    "type": "function"
  },
  {
    "inputs": [
      {
        "internalType": "uint256",
        "name": "_pid",
        "type": "uint256"
      },
      {
        "internalType": "uint256",
        "name": "_allocPoint",
        "type": "uint256"
      }
    ],
    "name": "set",
    "outputs": [],
    "stateMutability": "nonpayable",
    "type": "function"
  },
  {
    "inputs": [
      {
        "internalType": "address",
        "name": "_timelock",
        "type": "address"
      }
    ],
    "name": "setTimelock",
    "outputs": [],
    "stateMutability": "nonpayable",
    "type": "function"
  },
  {
    "inputs": [
      {
        "internalType": "uint256",
        "name": "_unstakingFrozenTime",
        "type": "uint256"
      }
    ],
    "name": "setUnstakingFrozenTime",
    "outputs": [],
    "stateMutability": "nonpayable",
    "type": "function"
  },
  {
    "inputs": [
      {
        "internalType": "address",
        "name": "_account",
        "type": "address"
      },
      {
        "internalType": "bool",
        "name": "_whitelisted",
        "type": "bool"
      }
    ],
    "name": "setWhitelisted",
    "outputs": [],
    "stateMutability": "nonpayable",
    "type": "function"
  },
  {
    "inputs": [
      {
        "internalType": "uint256",
        "name": "_pid",
        "type": "uint256"
      },
      {
        "internalType": "address",
        "name": "_user",
        "type": "address"
      }
    ],
    "name": "stakedWantTokens",
    "outputs": [
      {
        "internalType": "uint256",
        "name": "",
        "type": "uint256"
      }
    ],
    "stateMutability": "view",
    "type": "function"
  },
  {
    "inputs": [],
    "name": "startBlock",
    "outputs": [
      {
        "internalType": "uint256",
        "name": "",
        "type": "uint256"
      }
    ],
    "stateMutability": "view",
    "type": "function"
  },
  {
    "inputs": [],
    "name": "timelock",
    "outputs": [
      {
        "internalType": "address",
        "name": "",
        "type": "address"
      }
    ],
    "stateMutability": "view",
    "type": "function"
  },
  {
    "inputs": [],
    "name": "totalAllocPoint",
    "outputs": [
      {
        "internalType": "uint256",
        "name": "",
        "type": "uint256"
      }
    ],
    "stateMutability": "view",
    "type": "function"
  },
  {
    "inputs": [
      {
        "internalType": "uint256",
        "name": "_pid",
        "type": "uint256"
      },
      {
        "internalType": "address",
        "name": "_account",
        "type": "address"
      }
    ],
    "name": "unfrozenStakeTime",
    "outputs": [
      {
        "internalType": "uint256",
        "name": "",
        "type": "uint256"
      }
    ],
    "stateMutability": "view",
    "type": "function"
  },
  {
    "inputs": [],
    "name": "unstakingFrozenTime",
    "outputs": [
      {
        "internalType": "uint256",
        "name": "",
        "type": "uint256"
      }
    ],
    "stateMutability": "view",
    "type": "function"
  },
  {
    "inputs": [
      {
        "internalType": "uint256",
        "name": "_pid",
        "type": "uint256"
      }
    ],
    "name": "updatePool",
    "outputs": [],
    "stateMutability": "nonpayable",
    "type": "function"
  },
  {
    "inputs": [
      {
        "internalType": "uint256",
        "name": "_rewardPid",
        "type": "uint256"
      },
      {
        "internalType": "uint256",
        "name": "_rewardPerBlock",
        "type": "uint256"
      }
    ],
    "name": "updateRewardPerBlock",
    "outputs": [],
    "stateMutability": "nonpayable",
    "type": "function"
  },
  {
    "inputs": [
      {
        "internalType": "uint256",
        "name": "",
        "type": "uint256"
      },
      {
        "internalType": "address",
        "name": "",
        "type": "address"
      }
    ],
    "name": "userInfo",
    "outputs": [
      {
        "internalType": "uint256",
        "name": "shares",
        "type": "uint256"
      },
      {
        "internalType": "uint256",
        "name": "lastStakeTime",
        "type": "uint256"
      }
    ],
    "stateMutability": "view",
    "type": "function"
  },
  {
    "inputs": [
      {
        "internalType": "address",
        "name": "",
        "type": "address"
      }
    ],
    "name": "whitelisted",
    "outputs": [
      {
        "internalType": "bool",
        "name": "",
        "type": "bool"
      }
    ],
    "stateMutability": "view",
    "type": "function"
  },
  {
    "inputs": [
      {
        "internalType": "uint256",
        "name": "_pid",
        "type": "uint256"
      },
      {
        "internalType": "uint256",
        "name": "_wantAmt",
        "type": "uint256"
      }
    ],
    "name": "withdraw",
    "outputs": [],
    "stateMutability": "nonpayable",
    "type": "function"
  },
  {
    "inputs": [
      {
        "internalType": "uint256",
        "name": "_pid",
        "type": "uint256"
      }
    ],
    "name": "withdrawAll",
    "outputs": [],
    "stateMutability": "nonpayable",
    "type": "function"
  }
]